redis_metrics/__init__.py
redis_metrics/apps.py
redis_metrics/forms.py
redis_metrics/models.py
redis_metrics/settings.py
redis_metrics/urls.py
redis_metrics/utils.py
redis_metrics/views.py
redis_metrics/management/__init__.py
redis_metrics/management/commands/__init__.py
redis_metrics/management/commands/delete_gauge.py
redis_metrics/management/commands/delete_metric.py
redis_metrics/management/commands/fix_redis_metrics_keys.py
redis_metrics/management/commands/generate_test_metrics.py
redis_metrics/management/commands/redis_metrics_send_mail.py
redis_metrics/management/commands/reset_weekly_metrics.py
redis_metrics/management/commands/system_metric.py
redis_metrics/static/redis_metrics/css/bs-theme.min.css
redis_metrics/static/redis_metrics/css/bs.min.css
redis_metrics/static/redis_metrics/js/chart.min.js
redis_metrics/static/redis_metrics/js/colors.js
redis_metrics/static/redis_metrics/js/zepto.min.js
redis_metrics/templates/redis_metrics/_aggregate_detail.html
redis_metrics/templates/redis_metrics/_aggregate_history.html
redis_metrics/templates/redis_metrics/_gauge.html
redis_metrics/templates/redis_metrics/_metric_detail.html
redis_metrics/templates/redis_metrics/_metric_history.html
redis_metrics/templates/redis_metrics/_metric_list.html
redis_metrics/templates/redis_metrics/_since.html
redis_metrics/templates/redis_metrics/aggregate.html
redis_metrics/templates/redis_metrics/aggregate_detail.html
redis_metrics/templates/redis_metrics/aggregate_history.html
redis_metrics/templates/redis_metrics/base.html
redis_metrics/templates/redis_metrics/categorize.html
redis_metrics/templates/redis_metrics/default.html
redis_metrics/templates/redis_metrics/gauges.html
redis_metrics/templates/redis_metrics/metric_detail.html
redis_metrics/templates/redis_metrics/metric_history.html
redis_metrics/templates/redis_metrics/metrics_list.html
redis_metrics/templates/redis_metrics/email/report.html
redis_metrics/templates/redis_metrics/email/report.txt
django_redis_metrics-2.2.0.dist-info/AUTHORS.rst
django_redis_metrics-2.2.0.dist-info/LICENSE.txt
django_redis_metrics-2.2.0.dist-info/METADATA
django_redis_metrics-2.2.0.dist-info/WHEEL
django_redis_metrics-2.2.0.dist-info/top_level.txt
django_redis_metrics-2.2.0.dist-info/RECORD
