Metadata-Version: 2.1
Name: django-redis-metrics
Version: 2.2.0
Summary: django-redis-metrics is a Django application for tracking application metrics backed by Redis.
Author-email: Brad Montgomery <brad@bradmontgomery.net>
License: MIT
Project-URL: Homepage, https://github.com/bradmontgomery/django-redis_metrics
Project-URL: Bug Tracker, https://github.com/bradmontgomery/django-redis_metrics/issues
Keywords: django,redis_metrics,redis,metrics,performance
Classifier: Development Status :: 4 - Beta
Classifier: Environment :: Web Environment
Classifier: Intended Audience :: Developers
Classifier: License :: OSI Approved :: MIT License
Classifier: Operating System :: OS Independent
Classifier: Programming Language :: Python
Classifier: Programming Language :: Python :: 3
Classifier: Programming Language :: Python :: 3.8
Classifier: Programming Language :: Python :: 3.9
Classifier: Programming Language :: Python :: 3.10
Classifier: Programming Language :: Python :: 3.11
Classifier: Framework :: Django
Requires-Python: >=3.8
License-File: LICENSE.txt
License-File: AUTHORS.rst
Requires-Dist: django
Requires-Dist: redis
